src/arguments.py
src/custom_logging.py
src/main.py
src/paths.py
src/radio_controller.py
src/resources/default_settings.json
src/resources/radios_default/dummy_rx.json
src/resources/radios_default/dummy_tx.json
src/resources/radios_default/sdr.json
src/resources/rotors_default/dummy.json
src/resources/rotors_default/pe1ckk.json
src/rotor_controller.py
src/settings.py
src/test.py
src/tle.py
src/tracking.py
src/transponders.py
src/util.py
satgs-0.4.5.dist-info/METADATA
satgs-0.4.5.dist-info/WHEEL
satgs-0.4.5.dist-info/entry_points.txt
satgs-0.4.5.dist-info/licenses/LICENSE
satgs-0.4.5.dist-info/RECORD
