Metadata-Version: 2.4
Name: satgs
Version: 0.4.5
Summary: A command line tool that controls radios and rotors for amateur satellite operation.
License-Expression: GPL-3.0-or-later
License-File: LICENSE
Author: DB8LE
Author-email: db8le@darc.de
Requires-Python: <4.0,>=3.10
Classifier: Programming Language :: Python :: 3
Classifier: Programming Language :: Python :: 3.10
Classifier: Programming Language :: Python :: 3.11
Classifier: Programming Language :: Python :: 3.12
Classifier: Programming Language :: Python :: 3.13
Classifier: Programming Language :: Python :: 3.14
Requires-Dist: importlib-resources (>=6.5.2,<7.0.0)
Requires-Dist: numpy (>=2.1.0)
Requires-Dist: platformdirs (>=4.3.8,<5.0.0)
Requires-Dist: requests (>=2.32.4,<3.0.0)
Requires-Dist: skyfield (>=1.53,<2.0)
Project-URL: Documentation, https://satgs.readthedocs.io/en/latest/
Project-URL: Repository, https://github.com/DB8LE/satgs
Project-URL: issues, https://github.com/DB8LE/satgs/issues
